[
  {
    "id": "8491",
    "title": "Existing Post is updated",
    "slug": "existing-post-is-updated",
    "link": "https://infolegalge-fcztd.wpcomstaging.com/?psppnotif_workflow=existing-post-is-updated",
    "content": "",
    "excerpt": "",
    "creator": "infolegalge",
    "date": "2025-08-22 12:49:03",
    "categories": []
  },
  {
    "id": "8492",
    "title": "New Post is created in Draft status",
    "slug": "new-post-is-created-in-draft-status",
    "link": "https://infolegalge-fcztd.wpcomstaging.com/?psppnotif_workflow=new-post-is-created-in-draft-status",
    "content": "",
    "excerpt": "",
    "creator": "infolegalge",
    "date": "2025-08-22 12:49:03",
    "categories": []
  },
  {
    "id": "8493",
    "title": "New Post is Published",
    "slug": "new-post-is-published",
    "link": "https://infolegalge-fcztd.wpcomstaging.com/?psppnotif_workflow=new-post-is-published",
    "content": "",
    "excerpt": "",
    "creator": "infolegalge",
    "date": "2025-08-22 12:49:03",
    "categories": []
  }
]